setup.cfg
setup.py
confman/__init__.py
confman/confman.py
file2conf.egg-info/PKG-INFO
file2conf.egg-info/SOURCES.txt
file2conf.egg-info/dependency_links.txt
file2conf.egg-info/requires.txt
file2conf.egg-info/top_level.txt