Metadata-Version: 1.1
Name: file2conf
Version: 0.1.2
Summary: Lib for reading configs
Home-page: https://github.com/KTSStudio/confman
Author: KTS
Author-email: file2conf@ktsstudio.ru
License: MIT
Download-URL: https://github.com/KTSStudio/confman/tarball/0.1.2
Keywords: configs yaml json python
Platform: UNKNOWN
Classifier: Development Status :: 3 - Alpha
Classifier: Intended Audience :: Developers
Classifier: Topic :: Software Development :: Build Tools
Classifier: License :: OSI Approved :: MIT License
Classifier: Programming Language :: Python :: 3.4
Classifier: Programming Language :: Python :: 3.5
